[
    {
        "type": "message",
        "user": "U4F33615G",
        "text": "Onw",
        "ts": "1489527635.187131"
    },
    {
        "type": "message",
        "user": "U4FP56WS2",
        "text": "where are u？",
        "ts": "1489527648.190206"
    },
    {
        "type": "message",
        "user": "U4ECJHCC9",
        "text": "I combined the Trello boards into one.",
        "ts": "1489538340.902794"
    },
    {
        "type": "message",
        "user": "U4ECJHCC9",
        "text": "<https:\/\/trello.com\/b\/3sHmkiUb\/okclone>",
        "ts": "1489538341.902931"
    },
    {
        "type": "message",
        "user": "U4F6F54ER",
        "text": "",
        "bot_id": "B4ECG1FKJ",
        "attachments": [
            {
                "author_name": "Board",
                "callback_id": "callback-idBoard:58bf2d8939fff86b7bbeba3a-ts:1489538341938",
                "fallback": "OkClone (<https:\/\/trello.com\/b\/3sHmkiUb>)",
                "title": "OkClone",
                "id": 1,
                "title_link": "https:\/\/trello.com\/b\/3sHmkiUb",
                "author_icon": "https:\/\/trello.com\/dynamic-favicon?background=green&tiled=0&unread=0",
                "color": "519839",
                "actions": [
                    {
                        "id": "1",
                        "name": "join",
                        "text": "Join",
                        "type": "button",
                        "value": "{\"idBoard\":\"58bf2d8939fff86b7bbeba3a\"}",
                        "style": ""
                    },
                    {
                        "id": "2",
                        "name": "subscribe",
                        "text": "Subscribe",
                        "type": "button",
                        "value": "{\"idBoard\":\"58bf2d8939fff86b7bbeba3a\"}",
                        "style": ""
                    },
                    {
                        "id": "3",
                        "name": "star",
                        "text": ":star:",
                        "type": "button",
                        "value": "{\"idBoard\":\"58bf2d8939fff86b7bbeba3a\"}",
                        "style": ""
                    }
                ]
            }
        ],
        "ts": "1489538342.903082"
    },
    {
        "type": "message",
        "user": "U4ECJHCC9",
        "text": "I moved our tasks for this week into 'In Progress'. When you finish it, move it into 'Week 3'.",
        "ts": "1489538374.906726"
    },
    {
        "type": "message",
        "user": "U4ECJHCC9",
        "text": "Or if you finish it later, put it in whatever week it was completed.",
        "ts": "1489538390.908697"
    },
    {
        "type": "message",
        "user": "U4FP56WS2",
        "text": "copy that！ XD",
        "ts": "1489544841.582874"
    }
]